sevenapps/__init__.py
sevenapps/services/__init__.py
sevenapps/services/chatgpt_service_connector.py
sevenapps/services/google_firestore_connector.py
sevenapps/services/google_places_connector.py
sevenapps/services/google_services_connector.py
sevenapps/services/my_jdownloader_connector.py
sevenapps/services/plex_connector.py
sevenapps/services/selenium_connector.py
sevenapps/services/ssh_connector.py
sevenapps/utils/__init__.py
sevenapps/utils/app_selector.py
sevenapps/utils/custom_print.py
sevenapps/utils/data_manager.py
sevenapps/utils/file_manager.py
sevenapps_py_easy-0.0.20.dist-info/licenses/LICENSE
sevenapps_py_easy-0.0.20.dist-info/METADATA
sevenapps_py_easy-0.0.20.dist-info/WHEEL
sevenapps_py_easy-0.0.20.dist-info/top_level.txt
sevenapps_py_easy-0.0.20.dist-info/RECORD
