Metadata-Version: 2.4
Name: sevenapps-py-easy
Version: 0.0.20
Summary: Paquete creado para optimizar mi trabajo con python unificando lo más necesitado
Home-page: https://github.com/juanjp1992/sevenapps-py-easy.git
Author: SevenApps Studio
Author-email: sevenapps.studio@gmail.com
License: MIT
License-File: LICENSE
Requires-Dist: google-cloud-firestore
Requires-Dist: firebase-admin
Requires-Dist: selenium
Requires-Dist: gspread
Requires-Dist: scp
Requires-Dist: myjdapi
Requires-Dist: PlexAPI
Requires-Dist: openai
Dynamic: author
Dynamic: author-email
Dynamic: home-page
Dynamic: license
Dynamic: license-file
Dynamic: requires-dist
Dynamic: summary
